README.md
setup.cfg
setup.py
Katsubo_Stas_ORM.egg-info/PKG-INFO
Katsubo_Stas_ORM.egg-info/SOURCES.txt
Katsubo_Stas_ORM.egg-info/dependency_links.txt
Katsubo_Stas_ORM.egg-info/requires.txt
Katsubo_Stas_ORM.egg-info/top_level.txt
py2sql/__init__.py
py2sql/py2sql.py
test/__init__.py