Metadata-Version: 2.1
Name: Katsubo-Stas-ORM
Version: 0.0.3
Summary: A toy ORM tool
Home-page: UNKNOWN
Author: Katsubo Stas
Author-email: stasio850@gmail.com
License: UNKNOWN
Platform: UNKNOWN
Classifier: Programming Language :: Python :: 3
Classifier: License :: OSI Approved :: MIT License
Classifier: Operating System :: OS Independent
Requires-Python: >=3.8
